opengateway_sandbox_sdk/__init__.py
opengateway_sandbox_sdk/base.py
opengateway_sandbox_sdk/clientcredentials.py
opengateway_sandbox_sdk/devicelocation.py
opengateway_sandbox_sdk/httpclient.py
opengateway_sandbox_sdk/numberverification.py
opengateway_sandbox_sdk/purposes.py
opengateway_sandbox_sdk/qodhome.py
opengateway_sandbox_sdk/settings.py
opengateway_sandbox_sdk/simswap.py
opengateway_sandbox_sdk-1.1.0.dist-info/METADATA
opengateway_sandbox_sdk-1.1.0.dist-info/WHEEL
opengateway_sandbox_sdk-1.1.0.dist-info/licenses/LICENSE-2.0.txt
opengateway_sandbox_sdk-1.1.0.dist-info/RECORD
