Metadata-Version: 2.3
Name: opengateway-sandbox-sdk
Version: 1.1.0
Summary: OpenGateway Sandbox SDK
Project-URL: Homepage, https://opengateway.telefonica.com/
Project-URL: Documentation, https://opengateway.telefonica.com/en/apis
Author-email: OGEX <ogex@telefonica.com>
Maintainer-email: OGEX <ogex@telefonica.com>
License: 
License-File: LICENSE-2.0.txt
Keywords: OpenGateway,sdk
Classifier: Development Status :: 4 - Beta
Classifier: Programming Language :: Python
Requires-Python: >=3.10
Requires-Dist: requests
